{
	"credit": "Made by lavafoxerex",
	"textures": {
		"0": "rpg/gadget/small_potion/bottle",
		"1": "rpg/gadget/small_potion/red",
		"particle": "rpg/gadget/small_potion/bottle"
	},
	"elements": [
		{
			"from": [5, 0, 5],
			"to": [11, 8, 11],
			"rotation": {"angle": 0, "axis": "y", "origin": [5, 0, 5]},
			"faces": {
				"north": {"uv": [0, 5, 6, 13], "texture": "#0"},
				"east": {"uv": [0, 5, 6, 13], "texture": "#0"},
				"south": {"uv": [0, 5, 6, 13], "texture": "#0"},
				"west": {"uv": [0, 5, 6, 13], "texture": "#0"},
				"up": {"uv": [0, 0, 6, 6], "texture": "#0"},
				"down": {"uv": [6, 6, 12, 12], "texture": "#0"}
			}
		},
		{
			"from": [6, 9, 6],
			"to": [10, 11, 10],
			"rotation": {"angle": 0, "axis": "y", "origin": [5, 0, 5]},
			"faces": {
				"north": {"uv": [5, 2, 9, 4], "texture": "#0"},
				"east": {"uv": [8, 2, 12, 4], "texture": "#0"},
				"south": {"uv": [5, 2, 9, 4], "texture": "#0"},
				"west": {"uv": [8, 2, 12, 4], "texture": "#0"},
				"up": {"uv": [8, 2, 12, 6], "texture": "#0"},
				"down": {"uv": [8, 2, 12, 6], "texture": "#0"}
			}
		},
		{
			"from": [6.5, 8, 6.5],
			"to": [9.5, 9, 9.5],
			"rotation": {"angle": 0, "axis": "y", "origin": [4.5, 0, 5.5]},
			"faces": {
				"north": {"uv": [7, 0, 10, 1], "texture": "#0"},
				"east": {"uv": [5, 0, 8, 1], "texture": "#0"},
				"south": {"uv": [7, 0, 10, 1], "texture": "#0"},
				"west": {"uv": [5, 0, 8, 1], "texture": "#0"},
				"up": {"uv": [13, 3, 16, 6], "texture": "#0"},
				"down": {"uv": [13, 3, 16, 6], "texture": "#0"}
			}
		},
		{
			"from": [6.5, 11, 6.5],
			"to": [9.5, 12, 9.5],
			"rotation": {"angle": 0, "axis": "y", "origin": [4.5, 0, 5.5]},
			"faces": {
				"north": {"uv": [13, 0, 16, 1], "texture": "#0"},
				"east": {"uv": [13, 0, 16, 1], "texture": "#0"},
				"south": {"uv": [13, 0, 16, 1], "texture": "#0"},
				"west": {"uv": [13, 0, 16, 1], "texture": "#0"},
				"up": {"uv": [13, 0, 16, 3], "texture": "#0"},
				"down": {"uv": [13, 0, 16, 3], "texture": "#0"}
			}
		},
		{
			"from": [5.05, 0.05, 5.05],
			"to": [10.95, 7.95, 10.95],
			"faces": {
				"north": {"uv": [0, 0, 5.9, 7.9], "texture": "#1"},
				"east": {"uv": [0, 0, 5.9, 7.9], "texture": "#1"},
				"south": {"uv": [0, 0, 5.9, 7.9], "texture": "#1"},
				"west": {"uv": [0, 0, 5.9, 7.9], "texture": "#1"},
				"up": {"uv": [0, 0, 5.9, 5.9], "texture": "#1"},
				"down": {"uv": [0, 0, 5.9, 5.9], "texture": "#1"}
			}
		}
	],
	"display": {
		"thirdperson_righthand": {
			"translation": [0, 3.25, 2],
			"scale": [0.5, 0.5, 0.5]
		},
		"thirdperson_lefthand": {
			"translation": [0, 3.25, 2],
			"scale": [0.5, 0.5, 0.5]
		},
		"firstperson_righthand": {
			"rotation": [-12.5, 12.5, 19.25],
			"translation": [0, 5, 0],
			"scale": [0.6, 0.6, 0.6]
		},
		"firstperson_lefthand": {
			"rotation": [-12.5, 12.5, 19.25],
			"translation": [0, 5, 0],
			"scale": [0.6, 0.6, 0.6]
		},
		"ground": {
			"scale": [0.6, 0.6, 0.6]
		},
		"gui": {
			"rotation": [9.86, -20.54, -17.81],
			"translation": [0.5, 2.25, 0]
		},
		"head": {
			"translation": [0, -6, 0],
			"scale": [4, 4, 4]
		},
		"fixed": {
			"rotation": [0, 45, 0],
			"translation": [0, 2, 0]
		}
	},
	"groups": [
		{
			"name": "group",
			"origin": [4.5, 0, 5.5],
			"color": 0,
			"children": [0, 1, 2, 3]
		},
		4
	]
}